ESICelery/CeleryApps.py
ESICelery/__init__.py
ESICelery/__main__.py
ESICelery/__version__.py
ESICelery/celeryconfig.py
ESICelery/config.py
ESICelery/exceptions/__init__.py
ESICelery/exceptions/tasks.py
ESICelery/exceptions/utils.py
ESICelery/tasks/__init__.py
ESICelery/tasks/Alliance/AllianceInfo.py
ESICelery/tasks/Alliance/__init__.py
ESICelery/tasks/BaseTasks/BaseTask.py
ESICelery/tasks/BaseTasks/ESIResqust.py
ESICelery/tasks/BaseTasks/__init__.py
ESICelery/tasks/Character/CharacterPublicInfo.py
ESICelery/tasks/Character/__init__.py
ESICelery/tasks/Corporation/CorporationInfo.py
ESICelery/tasks/Corporation/__init__.py
ESICelery/tasks/Market/PricesList.py
ESICelery/tasks/Market/__init__.py
ESICelery/tasks/Routes/Route.py
ESICelery/tasks/Routes/__init__.py
ESICelery/tasks/Universe/CategoryInfo.py
ESICelery/tasks/Universe/ConstellationInfo.py
ESICelery/tasks/Universe/FactionsList.py
ESICelery/tasks/Universe/GroupInfo.py
ESICelery/tasks/Universe/RegionInfo.py
ESICelery/tasks/Universe/SystemInfo.py
ESICelery/tasks/Universe/TypeInfo.py
ESICelery/tasks/Universe/__init__.py
ESICelery/utils/ErrorLimiter.py
ESICelery/utils/RequestHeaders.py
ESICelery/utils/__init__.py
ESICelery-0.12.dist-info/LICENSE
ESICelery-0.12.dist-info/METADATA
ESICelery-0.12.dist-info/WHEEL
ESICelery-0.12.dist-info/top_level.txt
ESICelery-0.12.dist-info/RECORD
