Metadata-Version: 2.1
Name: ESICelery
Version: 0.12
Summary: ESI celery task queues for distributed API access using RabbitMQ and Redis.
Home-page: https://github.com/EVEInsight/ESICelery
Author-email: maintainers@eveinsight.net
License: GNU General Public License v3.0
Platform: UNKNOWN
Requires-Python: >=3.7
License-File: LICENSE
Requires-Dist: Celery (<6,>=5.2)
Requires-Dist: python-dateutil (<3,>=2.8.2)
Requires-Dist: redis (<5,>=4.1)
Requires-Dist: requests (<3,>=2.27)
